splintr/DataParallel.py
splintr/ModelParallel.py
splintr/__init__.py
splintr/benchmarks/__init__.py
splintr/benchmarks/benchmark.py
splintr/benchmarks/data_loader.py
splintr/benchmarks/models.py
splintr/dataparallel/__init__.py
splintr/dataparallel/isubnet.py
splintr/dataparallel/local_sgd.py
splintr/modelparallel/__init__.py
splintr/modelparallel/basic_model_parallel.py
splintr-0.0.5.dist-info/LICENSE
splintr-0.0.5.dist-info/METADATA
splintr-0.0.5.dist-info/WHEEL
splintr-0.0.5.dist-info/top_level.txt
splintr-0.0.5.dist-info/RECORD
